an_at_sync/__init__.py
an_at_sync/__main__.py
an_at_sync/actionnetwork.py
an_at_sync/cli.py
an_at_sync/conftest.py
an_at_sync/format.py
an_at_sync/model.py
an_at_sync/program.py
an_at_sync/wsgi.py
an_at_sync/wsgi_test.py
an_at_sync-0.9.2.dist-info/LICENSE
an_at_sync-0.9.2.dist-info/METADATA
an_at_sync-0.9.2.dist-info/WHEEL
an_at_sync-0.9.2.dist-info/entry_points.txt
an_at_sync-0.9.2.dist-info/top_level.txt
an_at_sync-0.9.2.dist-info/RECORD
